notebookvisu/__init__.py
notebookvisu/_version.py
notebookvisu-4.0.1.data/data/share/jupyter/labextensions/notebookvisu/package.json
notebookvisu-4.0.1.data/data/share/jupyter/labextensions/notebookvisu/schemas/notebookvisu/package.json.orig
notebookvisu-4.0.1.data/data/share/jupyter/labextensions/notebookvisu/schemas/notebookvisu/plugin.json
notebookvisu-4.0.1.data/data/share/jupyter/labextensions/notebookvisu/static/10.8076951dcd8a85bf1796.js
notebookvisu-4.0.1.data/data/share/jupyter/labextensions/notebookvisu/static/18.50cff49d6bc895deb3cf.js
notebookvisu-4.0.1.data/data/share/jupyter/labextensions/notebookvisu/static/18.50cff49d6bc895deb3cf.js.LICENSE.txt
notebookvisu-4.0.1.data/data/share/jupyter/labextensions/notebookvisu/static/308.865be8b4703baf6b341e.js
notebookvisu-4.0.1.data/data/share/jupyter/labextensions/notebookvisu/static/354.433a8fe6632782b20924.js
notebookvisu-4.0.1.data/data/share/jupyter/labextensions/notebookvisu/static/354.433a8fe6632782b20924.js.LICENSE.txt
notebookvisu-4.0.1.data/data/share/jupyter/labextensions/notebookvisu/static/39.5f65e541814b002fb28a.js
notebookvisu-4.0.1.data/data/share/jupyter/labextensions/notebookvisu/static/426.b484f257943e8b4bcce4.js
notebookvisu-4.0.1.data/data/share/jupyter/labextensions/notebookvisu/static/480.b244dc5dd0fd32cfc40a.js
notebookvisu-4.0.1.data/data/share/jupyter/labextensions/notebookvisu/static/546.8ebb7acb1fa093c0a3dc.js
notebookvisu-4.0.1.data/data/share/jupyter/labextensions/notebookvisu/static/563.ad560cb16986eae0d7a5.js
notebookvisu-4.0.1.data/data/share/jupyter/labextensions/notebookvisu/static/638.b927b2618bf342c948eb.js
notebookvisu-4.0.1.data/data/share/jupyter/labextensions/notebookvisu/static/702.90bfccf6924df2171e39.js
notebookvisu-4.0.1.data/data/share/jupyter/labextensions/notebookvisu/static/708.e449f772707d0bc44b1d.js
notebookvisu-4.0.1.data/data/share/jupyter/labextensions/notebookvisu/static/708.e449f772707d0bc44b1d.js.LICENSE.txt
notebookvisu-4.0.1.dist-info/METADATA
notebookvisu-4.0.1.dist-info/WHEEL
notebookvisu-4.0.1.dist-info/licenses/LICENSE
notebookvisu-4.0.1.dist-info/RECORD
